LICENSE
MANIFEST.in
README.md
pyproject.toml
setup.cfg
src/cadivi_analysis/__init__.py
src/cadivi_analysis/app.py
src/cadivi_analysis/settings.py
src/cadivi_analysis.egg-info/PKG-INFO
src/cadivi_analysis.egg-info/SOURCES.txt
src/cadivi_analysis.egg-info/dependency_links.txt
src/cadivi_analysis.egg-info/requires.txt
src/cadivi_analysis.egg-info/top_level.txt
src/cadivi_analysis/common/__init__.py
src/cadivi_analysis/common/config_const.py
src/cadivi_analysis/common/config_util.py
src/cadivi_analysis/common/singleton.py
src/cadivi_analysis/error_detector/__init__.py
src/cadivi_analysis/error_detector/error_detector.py
src/cadivi_analysis/utils/__init__.py
src/cadivi_analysis/utils/camera_utils.py
src/cadivi_analysis/utils/image_utils.py
src/cadivi_analysis/word_detector/__init__.py
src/cadivi_analysis/word_detector/word_detector.py
test/test_grab_image.py
test/test_grab_image_yolo.py
test/test_tesseract.py
test/test_yolov8.py